[
    {
        "number": "3713",
        "description": "Salmon Very Light",
        "rgbCode": "FFE2E2"
    },
    {
        "number": "761",
        "description": "Salmon Light",
        "rgbCode": "FFC9C9"
    },
    {
        "number": "760",
        "description": "Salmon",
        "rgbCode": "F5ADAD"
    },
    {
        "number": "3712",
        "description": "Salmon Medium",
        "rgbCode": "F18787"
    },
    {
        "number": "3328",
        "description": "Salmon Dark",
        "rgbCode": "E36D6D"
    },
    {
        "number": "347",
        "description": "Salmon Very Dark",
        "rgbCode": "BF2D2D"
    },
    {
        "number": "353",
        "description": "Peach",
        "rgbCode": "FED7CC"
    },
    {
        "number": "352",
        "description": "Coral Light",
        "rgbCode": "FD9C97"
    },
    {
        "number": "351",
        "description": "Coral",
        "rgbCode": "E96A67"
    },
    {
        "number": "350",
        "description": "Coral Medium",
        "rgbCode": "E04848"
    },
    {
        "number": "349",
        "description": "Coral Dark",
        "rgbCode": "D21035"
    },
    {
        "number": "817",
        "description": "Coral Red Very Dark",
        "rgbCode": "BB051F"
    },
    {
        "number": "3708",
        "description": "Melon Light",
        "rgbCode": "FFCBD5"
    },
    {
        "number": "3706",
        "description": "Melon Medium",
        "rgbCode": "FFADBC"
    },
    {
        "number": "3705",
        "description": "Melon Dark",
        "rgbCode": "FF7992"
    },
    {
        "number": "3801",
        "description": "Melon Very Dark",
        "rgbCode": "E74967"
    },
    {
        "number": "666",
        "description": "Bright Red",
        "rgbCode": "E31D42"
    },
    {
        "number": "321",
        "description": "Red",
        "rgbCode": "C72B3B"
    },
    {
        "number": "304",
        "description": "Red Medium",
        "rgbCode": "B71F33"
    },
    {
        "number": "498",
        "description": "Red Dark",
        "rgbCode": "A7132B"
    },
    {
        "number": "816",
        "description": "Garnet",
        "rgbCode": "970B23"
    },
    {
        "number": "815",
        "description": "Garnet Medium",
        "rgbCode": "87071F"
    },
    {
        "number": "814",
        "description": "Garnet Dark",
        "rgbCode": "7B001B"
    },
    {
        "number": "894",
        "description": "Carnation Very Light",
        "rgbCode": "FFB2BB"
    },
    {
        "number": "893",
        "description": "Carnation Light",
        "rgbCode": "FC90A2"
    },
    {
        "number": "892",
        "description": "Carnation Medium",
        "rgbCode": "FF798C"
    },
    {
        "number": "891",
        "description": "Carnation Dark",
        "rgbCode": "FF5773"
    },
    {
        "number": "818",
        "description": "Baby Pink",
        "rgbCode": "FFDFD9"
    },
    {
        "number": "957",
        "description": "Geranium Pale",
        "rgbCode": "FDB5B5"
    },
    {
        "number": "956",
        "description": "Geranium",
        "rgbCode": "FF9191"
    },
    {
        "number": "309",
        "description": "Rose Dark",
        "rgbCode": "BA4A4A"
    },
    {
        "number": "963",
        "description": "Dusty Rose Ult Vy Lt",
        "rgbCode": "FFD7D7"
    },
    {
        "number": "3716",
        "description": "Dusty Rose Med Vy Lt",
        "rgbCode": "FFBDBD"
    },
    {
        "number": "962",
        "description": "Dusty Rose Medium",
        "rgbCode": "E68A8A"
    },
    {
        "number": "961",
        "description": "Dusty Rose Dark",
        "rgbCode": "CF7373"
    },
    {
        "number": "3833",
        "description": "Raspberry Light",
        "rgbCode": "EA8699"
    },
    {
        "number": "3832",
        "description": "Raspberry Medium",
        "rgbCode": "DB556E"
    },
    {
        "number": "3831",
        "description": "Raspberry Dark",
        "rgbCode": "B32F48"
    },
    {
        "number": "777",
        "description": "Raspberry Very Dark",
        "rgbCode": "913546"
    },
    {
        "number": "819",
        "description": "Baby Pink Light",
        "rgbCode": "FFEEEB"
    },
    {
        "number": "3326",
        "description": "Rose Light",
        "rgbCode": "FBADB4"
    },
    {
        "number": "776",
        "description": "Pink Medium",
        "rgbCode": "FCB0B9"
    },
    {
        "number": "899",
        "description": "Rose Medium",
        "rgbCode": "F27688"
    },
    {
        "number": "335",
        "description": "Rose",
        "rgbCode": "EE546E"
    },
    {
        "number": "326",
        "description": "Rose Very Dark",
        "rgbCode": "B33B4B"
    },
    {
        "number": "151",
        "description": "Dusty Rose Vry Lt",
        "rgbCode": "F0CED4"
    },
    {
        "number": "3354",
        "description": "Dusty Rose Light",
        "rgbCode": "E4A6AC"
    },
    {
        "number": "3733",
        "description": "Dusty Rose",
        "rgbCode": "E8879B"
    },
    {
        "number": "3731",
        "description": "Dusty Rose Very Dark",
        "rgbCode": "DA6783"
    },
    {
        "number": "3350",
        "description": "Dusty Rose Ultra Dark",
        "rgbCode": "BC4365"
    },
    {
        "number": "150",
        "description": "Dusty Rose Ult Vy Dk",
        "rgbCode": "AB0249"
    },
    {
        "number": "3689",
        "description": "Mauve Light",
        "rgbCode": "FBBFC2"
    },
    {
        "number": "3688",
        "description": "Mauve Medium",
        "rgbCode": "E7A9AC"
    },
    {
        "number": "3687",
        "description": "Mauve",
        "rgbCode": "C96B70"
    },
    {
        "number": "3803",
        "description": "Mauve Dark",
        "rgbCode": "AB3357"
    },
    {
        "number": "3685",
        "description": "Mauve Very Dark",
        "rgbCode": "881531"
    },
    {
        "number": "605",
        "description": "Cranberry Very Light",
        "rgbCode": "FFC0CD"
    },
    {
        "number": "604",
        "description": "Cranberry Light",
        "rgbCode": "FFB0BE"
    },
    {
        "number": "603",
        "description": "Cranberry",
        "rgbCode": "FFA4BE"
    },
    {
        "number": "602",
        "description": "Cranberry Medium",
        "rgbCode": "E24874"
    },
    {
        "number": "601",
        "description": "Cranberry Dark",
        "rgbCode": "D1286A"
    },
    {
        "number": "600",
        "description": "Cranberry Very Dark",
        "rgbCode": "CD2F63"
    },
    {
        "number": "3806",
        "description": "Cyclamen Pink Light",
        "rgbCode": "FF8CAE"
    },
    {
        "number": "3805",
        "description": "Cyclamen Pink",
        "rgbCode": "F3478B"
    },
    {
        "number": "3804",
        "description": "Cyclamen Pink Dark",
        "rgbCode": "E02876"
    },
    {
        "number": "3609",
        "description": "Plum Ultra Light",
        "rgbCode": "F4AED7"
    },
    {
        "number": "3608",
        "description": "Plum Very Light",
        "rgbCode": "EA9CC4"
    },
    {
        "number": "3607",
        "description": "Plum Light",
        "rgbCode": "C54989"
    },
    {
        "number": "718",
        "description": "Plum",
        "rgbCode": "9C2462"
    },
    {
        "number": "917",
        "description": "Plum Medium",
        "rgbCode": "9B1359"
    },
    {
        "number": "915",
        "description": "Plum Dark",
        "rgbCode": "820043"
    },
    {
        "number": "225",
        "description": "Shell Pink Ult Vy Lt",
        "rgbCode": "FFDFD7"
    },
    {
        "number": "224",
        "description": "Shell Pink Very Light",
        "rgbCode": "EBB7AF"
    },
    {
        "number": "152",
        "description": "Shell Pink Med Light",
        "rgbCode": "E2A099"
    },
    {
        "number": "223",
        "description": "Shell Pink Light",
        "rgbCode": "CC847C"
    },
    {
        "number": "3722",
        "description": "Shell Pink Med",
        "rgbCode": "BC6C64"
    },
    {
        "number": "3721",
        "description": "Shell Pink Dark",
        "rgbCode": "A14B51"
    },
    {
        "number": "221",
        "description": "Shell Pink Vy Dk",
        "rgbCode": "883E45"
    },
    {
        "number": "778",
        "description": "Antique Mauve Vy Lt",
        "rgbCode": "DFB3BB"
    },
    {
        "number": "3727",
        "description": "Antique Mauve Light",
        "rgbCode": "DBA9B2"
    },
    {
        "number": "316",
        "description": "Antique Mauve Med",
        "rgbCode": "B7737F"
    },
    {
        "number": "3726",
        "description": "Antique Mauve Dark",
        "rgbCode": "9B5B66"
    },
    {
        "number": "315",
        "description": "Antique Mauve Md Dk",
        "rgbCode": "814952"
    },
    {
        "number": "3802",
        "description": "Antique Mauve Vy Dk",
        "rgbCode": "714149"
    },
    {
        "number": "902",
        "description": "Garnet Very Dark",
        "rgbCode": "822637"
    },
    {
        "number": "3743",
        "description": "Antique Violet Vy Lt",
        "rgbCode": "D7CBD3"
    },
    {
        "number": "3042",
        "description": "Antique Violet Light",
        "rgbCode": "B79DA7"
    },
    {
        "number": "3041",
        "description": "Antique Violet Medium",
        "rgbCode": "956F7C"
    },
    {
        "number": "3740",
        "description": "Antique Violet Dark",
        "rgbCode": "785762"
    },
    {
        "number": "3836",
        "description": "Grape Light",
        "rgbCode": "BA91AA"
    },
    {
        "number": "3835",
        "description": "Grape Medium",
        "rgbCode": "946083"
    },
    {
        "number": "3834",
        "description": "Grape Dark",
        "rgbCode": "72375D"
    },
    {
        "number": "154",
        "description": "Grape Very Dark",
        "rgbCode": "572433"
    },
    {
        "number": "211",
        "description": "Lavender Light",
        "rgbCode": "E3CBE3"
    },
    {
        "number": "210",
        "description": "Lavender Medium",
        "rgbCode": "D29FC3"
    },
    {
        "number": "209",
        "description": "Lavender Dark",
        "rgbCode": "A37BA7"
    },
    {
        "number": "208",
        "description": "Lavender Very Dark",
        "rgbCode": "835B8B"
    },
    {
        "number": "3837",
        "description": "Lavender Ultra Dark",
        "rgbCode": "6C3A6E"
    },
    {
        "number": "327",
        "description": "Violet Dark",
        "rgbCode": "633666"
    },
    {
        "number": "153",
        "description": "Violet Very Light",
        "rgbCode": "E6CCD9"
    },
    {
        "number": "554",
        "description": "Violet Light",
        "rgbCode": "DBB3CB"
    },
    {
        "number": "553",
        "description": "Violet",
        "rgbCode": "A3638B"
    },
    {
        "number": "552",
        "description": "Violet  Medium",
        "rgbCode": "803A6B"
    },
    {
        "number": "550",
        "description": "Violet Very Dark",
        "rgbCode": "5C184E"
    },
    {
        "number": "3747",
        "description": "Blue Violet Vy Lt",
        "rgbCode": "D3D7ED"
    },
    {
        "number": "341",
        "description": "Blue Violet Light",
        "rgbCode": "B7BFDD"
    },
    {
        "number": "156",
        "description": "Blue Violet Med Lt",
        "rgbCode": "A3AED1"
    },
    {
        "number": "340",
        "description": "Blue Violet Medium",
        "rgbCode": "ADA7C7"
    },
    {
        "number": "155",
        "description": "Blue Violet Med Dark",
        "rgbCode": "9891B6"
    },
    {
        "number": "3746",
        "description": "Blue Violet Dark",
        "rgbCode": "776B98"
    },
    {
        "number": "333",
        "description": "Blue Violet Very Dark",
        "rgbCode": "5C5478"
    },
    {
        "number": "157",
        "description": "Cornflower Blue Vy Lt",
        "rgbCode": "BBC3D9"
    },
    {
        "number": "794",
        "description": "Cornflower Blue Light",
        "rgbCode": "8F9CC1"
    },
    {
        "number": "793",
        "description": "Cornflower Blue Med",
        "rgbCode": "707DA2"
    },
    {
        "number": "3807",
        "description": "Cornflower Blue",
        "rgbCode": "60678C"
    },
    {
        "number": "792",
        "description": "Cornflower Blue Dark",
        "rgbCode": "555B7B"
    },
    {
        "number": "158",
        "description": "Cornflower Blu M V D",
        "rgbCode": "4C526E"
    },
    {
        "number": "791",
        "description": "Cornflower Blue V D",
        "rgbCode": "464563"
    },
    {
        "number": "3840",
        "description": "Lavender Blue Light",
        "rgbCode": "B0C0DA"
    },
    {
        "number": "3839",
        "description": "Lavender Blue Med",
        "rgbCode": "7B8EAB"
    },
    {
        "number": "3838",
        "description": "Lavender Blue Dark",
        "rgbCode": "5C7294"
    },
    {
        "number": "800",
        "description": "Delft Blue Pale",
        "rgbCode": "C0CCDE"
    },
    {
        "number": "809",
        "description": "Delft Blue",
        "rgbCode": "94A8C6"
    },
    {
        "number": "799",
        "description": "Delft Blue Medium",
        "rgbCode": "748EB6"
    },
    {
        "number": "798",
        "description": "Delft Blue Dark",
        "rgbCode": "466A8E"
    },
    {
        "number": "797",
        "description": "Royal Blue",
        "rgbCode": "13477D"
    },
    {
        "number": "796",
        "description": "Royal Blue Dark",
        "rgbCode": "11416D"
    },
    {
        "number": "820",
        "description": "Royal Blue Very Dark",
        "rgbCode": "0E365C"
    },
    {
        "number": "162",
        "description": "Blue Ultra Very Light",
        "rgbCode": "DBECF5"
    },
    {
        "number": "827",
        "description": "Blue Very Light",
        "rgbCode": "BDDDED"
    },
    {
        "number": "813",
        "description": "Blue Light",
        "rgbCode": "A1C2D7"
    },
    {
        "number": "826",
        "description": "Blue Medium",
        "rgbCode": "6B9EBF"
    },
    {
        "number": "825",
        "description": "Blue Dark",
        "rgbCode": "4781A5"
    },
    {
        "number": "824",
        "description": "Blue Very Dark",
        "rgbCode": "396987"
    },
    {
        "number": "996",
        "description": "Electric Blue Medium",
        "rgbCode": "30C2EC"
    },
    {
        "number": "3843",
        "description": "Electric Blue",
        "rgbCode": "14AAD0"
    },
    {
        "number": "995",
        "description": "Electric Blue Dark",
        "rgbCode": "2696B6"
    },
    {
        "number": "3846",
        "description": "Turquoise Bright Light",
        "rgbCode": "06E3E6"
    },
    {
        "number": "3845",
        "description": "Turquoise Bright Med",
        "rgbCode": "04C4CA"
    },
    {
        "number": "3844",
        "description": "Turquoise Bright Dark",
        "rgbCode": "12AEBA"
    },
    {
        "number": "159",
        "description": "Blue Gray Light",
        "rgbCode": "C7CAD7"
    },
    {
        "number": "160",
        "description": "Blue Gray Medium",
        "rgbCode": "999FB7"
    },
    {
        "number": "161",
        "description": "Blue Gray",
        "rgbCode": "7880A4"
    },
    {
        "number": "3756",
        "description": "Baby Blue Ult Vy Lt",
        "rgbCode": "EEFCFC"
    },
    {
        "number": "775",
        "description": "Baby Blue Very Light",
        "rgbCode": "D9EBF1"
    },
    {
        "number": "3841",
        "description": "Baby Blue Pale",
        "rgbCode": "CDDFED"
    },
    {
        "number": "3325",
        "description": "Baby Blue Light",
        "rgbCode": "B8D2E6"
    },
    {
        "number": "3755",
        "description": "Baby Blue",
        "rgbCode": "92B4CE"
    },
    {
        "number": "334",
        "description": "Baby Blue Medium",
        "rgbCode": "739FC1"
    },
    {
        "number": "322",
        "description": "Baby Blue Dark",
        "rgbCode": "5A8FB8"
    },
    {
        "number": "312",
        "description": "Baby Blue Very Dark",
        "rgbCode": "35668B"
    },
    {
        "number": "803",
        "description": "Baby Blue Ult Vy Dk",
        "rgbCode": "2C597C"
    },
    {
        "number": "336",
        "description": "Navy Blue",
        "rgbCode": "253B73"
    },
    {
        "number": "823",
        "description": "Navy Blue Dark",
        "rgbCode": "213063"
    },
    {
        "number": "939",
        "description": "Navy Blue Very Dark",
        "rgbCode": "1B2853"
    },
    {
        "number": "3753",
        "description": "Antique Blue Ult Vy Lt",
        "rgbCode": "DBE2E9"
    },
    {
        "number": "3752",
        "description": "Antique Blue Very Lt",
        "rgbCode": "C7D1DB"
    },
    {
        "number": "932",
        "description": "Antique Blue Light",
        "rgbCode": "A2B5C6"
    },
    {
        "number": "931",
        "description": "Antique Blue Medium",
        "rgbCode": "6A859E"
    },
    {
        "number": "930",
        "description": "Antique Blue Dark",
        "rgbCode": "455C71"
    },
    {
        "number": "3750",
        "description": "Antique Blue Very Dk",
        "rgbCode": "384C5E"
    },
    {
        "number": "828",
        "description": "Sky Blue Vy Lt",
        "rgbCode": "C5E8ED"
    },
    {
        "number": "3761",
        "description": "Sky Blue Light",
        "rgbCode": "ACD8E2"
    },
    {
        "number": "519",
        "description": "Sky Blue",
        "rgbCode": "7EB1C8"
    },
    {
        "number": "518",
        "description": "Wedgewood Light",
        "rgbCode": "4F93A7"
    },
    {
        "number": "3760",
        "description": "Wedgewood Med",
        "rgbCode": "3E85A2"
    },
    {
        "number": "517",
        "description": "Wedgewood Dark",
        "rgbCode": "3B768F"
    },
    {
        "number": "3842",
        "description": "Wedgewood Vry Dk",
        "rgbCode": "32667C"
    },
    {
        "number": "311",
        "description": "Wedgewood Ult VyDk",
        "rgbCode": "1C5066"
    },
    {
        "number": "747",
        "description": "Peacock Blue Vy Lt",
        "rgbCode": "E5FCFD"
    },
    {
        "number": "3766",
        "description": "Peacock Blue Light",
        "rgbCode": "99CFD9"
    },
    {
        "number": "807",
        "description": "Peacock Blue",
        "rgbCode": "64ABBA"
    },
    {
        "number": "806",
        "description": "Peacock Blue Dark",
        "rgbCode": "3D95A5"
    },
    {
        "number": "3765",
        "description": "Peacock Blue Vy Dk",
        "rgbCode": "347F8C"
    },
    {
        "number": "3811",
        "description": "Turquoise Very Light",
        "rgbCode": "BCE3E6"
    },
    {
        "number": "598",
        "description": "Turquoise Light",
        "rgbCode": "90C3CC"
    },
    {
        "number": "597",
        "description": "Turquoise",
        "rgbCode": "5BA3B3"
    },
    {
        "number": "3810",
        "description": "Turquoise Dark",
        "rgbCode": "488E9A"
    },
    {
        "number": "3809",
        "description": "Turquoise Vy Dark",
        "rgbCode": "3F7C85"
    },
    {
        "number": "3808",
        "description": "Turquoise Ult Vy Dk",
        "rgbCode": "366970"
    },
    {
        "number": "928",
        "description": "Gray Green Vy Lt",
        "rgbCode": "DDE3E3"
    },
    {
        "number": "927",
        "description": "Gray Green Light",
        "rgbCode": "BDCBCB"
    },
    {
        "number": "926",
        "description": "Gray Green Med",
        "rgbCode": "98AEAE"
    },
    {
        "number": "3768",
        "description": "Gray Green Dark",
        "rgbCode": "657F7F"
    },
    {
        "number": "924",
        "description": "Gray Green Vy Dark",
        "rgbCode": "566A6A"
    },
    {
        "number": "3849",
        "description": "Teal Green Light",
        "rgbCode": "52B3AE"
    },
    {
        "number": "3848",
        "description": "Teal Green Med",
        "rgbCode": "419392"
    },
    {
        "number": "3847",
        "description": "Teal Green Dark",
        "rgbCode": "347D75"
    },
    {
        "number": "964",
        "description": "Sea Green Light",
        "rgbCode": "A9E2D8"
    },
    {
        "number": "959",
        "description": "Sea Green Med",
        "rgbCode": "59C7B4"
    },
    {
        "number": "958",
        "description": "Sea Green Dark",
        "rgbCode": "3EB6A1"
    },
    {
        "number": "3812",
        "description": "Sea Green Vy Dk",
        "rgbCode": "2F8C84"
    },
    {
        "number": "3851",
        "description": "Green Bright Lt",
        "rgbCode": "49B3A1"
    },
    {
        "number": "943",
        "description": "Green Bright Md",
        "rgbCode": "3D9384"
    },
    {
        "number": "3850",
        "description": "Green Bright Dk",
        "rgbCode": "378477"
    },
    {
        "number": "993",
        "description": "Aquamarine Vy Lt",
        "rgbCode": "90C0B4"
    },
    {
        "number": "992",
        "description": "Aquamarine Lt",
        "rgbCode": "6FAE9F"
    },
    {
        "number": "3814",
        "description": "Aquamarine",
        "rgbCode": "508B7D"
    },
    {
        "number": "991",
        "description": "Aquamarine Dk",
        "rgbCode": "477B6E"
    },
    {
        "number": "966",
        "description": "Jade Ultra Vy Lt",
        "rgbCode": "B9D7C0"
    },
    {
        "number": "564",
        "description": "Jade Very Light",
        "rgbCode": "A7CDAF"
    },
    {
        "number": "563",
        "description": "Jade Light",
        "rgbCode": "8FC098"
    },
    {
        "number": "562",
        "description": "Jade Medium",
        "rgbCode": "53976A"
    },
    {
        "number": "505",
        "description": "Jade Green",
        "rgbCode": "338362"
    },
    {
        "number": "3817",
        "description": "Celadon Green Lt",
        "rgbCode": "99C3AA"
    },
    {
        "number": "3816",
        "description": "Celadon Green",
        "rgbCode": "65A57D"
    },
    {
        "number": "163",
        "description": "Celadon Green Md",
        "rgbCode": "4D8361"
    },
    {
        "number": "3815",
        "description": "Celadon Green Dk",
        "rgbCode": "477759"
    },
    {
        "number": "561",
        "description": "Celadon Green VD",
        "rgbCode": "2C6A45"
    },
    {
        "number": "504",
        "description": "Blue Green Vy Lt",
        "rgbCode": "C4DECC"
    },
    {
        "number": "3813",
        "description": "Blue Green Lt",
        "rgbCode": "B2D4BD"
    },
    {
        "number": "503",
        "description": "Blue Green Med",
        "rgbCode": "7BAC94"
    },
    {
        "number": "502",
        "description": "Blue Green",
        "rgbCode": "5B9071"
    },
    {
        "number": "501",
        "description": "Blue Green Dark",
        "rgbCode": "396F52"
    },
    {
        "number": "500",
        "description": "Blue Green Vy Dk",
        "rgbCode": "044D33"
    },
    {
        "number": "955",
        "description": "Nile Green Light",
        "rgbCode": "A2D6AD"
    },
    {
        "number": "954",
        "description": "Nile Green",
        "rgbCode": "88BA91"
    },
    {
        "number": "913",
        "description": "Nile Green Med",
        "rgbCode": "6DAB77"
    },
    {
        "number": "912",
        "description": "Emerald Green Lt",
        "rgbCode": "1B9D6B"
    },
    {
        "number": "911",
        "description": "Emerald Green Med",
        "rgbCode": "189065"
    },
    {
        "number": "910",
        "description": "Emerald Green Dark",
        "rgbCode": "187E56"
    },
    {
        "number": "909",
        "description": "Emerald Green Vy Dk",
        "rgbCode": "156F49"
    },
    {
        "number": "3818",
        "description": "Emerald Grn Ult V Dk",
        "rgbCode": "115A3B"
    },
    {
        "number": "369",
        "description": "Pistachio Green Vy Lt",
        "rgbCode": "D7EDCC"
    },
    {
        "number": "368",
        "description": "Pistachio Green Lt",
        "rgbCode": "A6C298"
    },
    {
        "number": "320",
        "description": "Pistachio Green Med",
        "rgbCode": "69885A"
    },
    {
        "number": "367",
        "description": "Pistachio Green Dk",
        "rgbCode": "617A52"
    },
    {
        "number": "319",
        "description": "Pistachio Grn Vy Dk",
        "rgbCode": "205F2E"
    },
    {
        "number": "890",
        "description": "Pistachio Grn Ult V D",
        "rgbCode": "184923"
    },
    {
        "number": "164",
        "description": "Forest Green Lt",
        "rgbCode": "C8D8B8"
    },
    {
        "number": "989",
        "description": "Forest Green",
        "rgbCode": "8DA675"
    },
    {
        "number": "988",
        "description": "Forest Green Med",
        "rgbCode": "738B5B"
    },
    {
        "number": "987",
        "description": "Forest Green Dk",
        "rgbCode": "587141"
    },
    {
        "number": "986",
        "description": "Forest Green Vy Dk",
        "rgbCode": "405230"
    },
    {
        "number": "772",
        "description": "Yellow Green Vy Lt",
        "rgbCode": "E4ECD4"
    },
    {
        "number": "3348",
        "description": "Yellow Green Lt",
        "rgbCode": "CCD9B1"
    },
    {
        "number": "3347",
        "description": "Yellow Green Med",
        "rgbCode": "71935C"
    },
    {
        "number": "3346",
        "description": "Hunter Green",
        "rgbCode": "406A3A"
    },
    {
        "number": "3345",
        "description": "Hunter Green Dk",
        "rgbCode": "1B5915"
    },
    {
        "number": "895",
        "description": "Hunter Green Vy Dk",
        "rgbCode": "1B5300"
    },
    {
        "number": "704",
        "description": "Chartreuse Bright",
        "rgbCode": "9ECF34"
    },
    {
        "number": "703",
        "description": "Chartreuse",
        "rgbCode": "7BB547"
    },
    {
        "number": "702",
        "description": "Kelly Green",
        "rgbCode": "47A72F"
    },
    {
        "number": "701",
        "description": "Green Light",
        "rgbCode": "3F8F29"
    },
    {
        "number": "700",
        "description": "Green Bright",
        "rgbCode": "07731B"
    },
    {
        "number": "699",
        "description": "Green",
        "rgbCode": "056517"
    },
    {
        "number": "907",
        "description": "Parrot Green Lt",
        "rgbCode": "C7E666"
    },
    {
        "number": "906",
        "description": "Parrot Green Md",
        "rgbCode": "7FB335"
    },
    {
        "number": "905",
        "description": "Parrot Green Dk",
        "rgbCode": "628A28"
    },
    {
        "number": "904",
        "description": "Parrot Green V Dk",
        "rgbCode": "557822"
    },
    {
        "number": "472",
        "description": "Avocado Grn U Lt",
        "rgbCode": "D8E498"
    },
    {
        "number": "471",
        "description": "Avocado Grn V Lt",
        "rgbCode": "AEBF79"
    },
    {
        "number": "470",
        "description": "Avocado Grn Lt",
        "rgbCode": "94AB4F"
    },
    {
        "number": "469",
        "description": "Avocado Green",
        "rgbCode": "72843C"
    },
    {
        "number": "937",
        "description": "Avocado Green Md",
        "rgbCode": "627133"
    },
    {
        "number": "936",
        "description": "Avocado Grn V Dk",
        "rgbCode": "4C5826"
    },
    {
        "number": "935",
        "description": "Avocado Green Dk",
        "rgbCode": "424D21"
    },
    {
        "number": "934",
        "description": "Avocado Grn Black",
        "rgbCode": "313919"
    },
    {
        "number": "523",
        "description": "Fern Green Lt",
        "rgbCode": "ABB197"
    },
    {
        "number": "3053",
        "description": "Green Gray",
        "rgbCode": "9CA482"
    },
    {
        "number": "3052",
        "description": "Green Gray Md",
        "rgbCode": "889268"
    },
    {
        "number": "3051",
        "description": "Green Gray Dk",
        "rgbCode": "5F6648"
    },
    {
        "number": "524",
        "description": "Fern Green Vy Lt",
        "rgbCode": "C4CDAC"
    },
    {
        "number": "522",
        "description": "Fern Green",
        "rgbCode": "969E7E"
    },
    {
        "number": "520",
        "description": "Fern Green Dark",
        "rgbCode": "666D4F"
    },
    {
        "number": "3364",
        "description": "Pine Green",
        "rgbCode": "83975F"
    },
    {
        "number": "3363",
        "description": "Pine Green Md",
        "rgbCode": "728256"
    },
    {
        "number": "3362",
        "description": "Pine Green Dk",
        "rgbCode": "5E6B47"
    },
    {
        "number": "165",
        "description": "Moss Green Vy Lt",
        "rgbCode": "EFF4A4"
    },
    {
        "number": "3819",
        "description": "Moss Green Lt",
        "rgbCode": "E0E868"
    },
    {
        "number": "166",
        "description": "Moss Green Md Lt",
        "rgbCode": "C0C840"
    },
    {
        "number": "581",
        "description": "Moss Green",
        "rgbCode": "A7AE38"
    },
    {
        "number": "580",
        "description": "Moss Green Dk",
        "rgbCode": "888D33"
    },
    {
        "number": "734",
        "description": "Olive Green Lt",
        "rgbCode": "C7C077"
    },
    {
        "number": "733",
        "description": "Olive Green Md",
        "rgbCode": "BCB34C"
    },
    {
        "number": "732",
        "description": "Olive Green",
        "rgbCode": "948C36"
    },
    {
        "number": "731",
        "description": "Olive Green Dk",
        "rgbCode": "938B37"
    },
    {
        "number": "730",
        "description": "Olive Green V Dk",
        "rgbCode": "827B30"
    },
    {
        "number": "3013",
        "description": "Khaki Green Lt",
        "rgbCode": "B9B982"
    },
    {
        "number": "3012",
        "description": "Khaki Green Md",
        "rgbCode": "A6A75D"
    },
    {
        "number": "3011",
        "description": "Khaki Green Dk",
        "rgbCode": "898A58"
    },
    {
        "number": "372",
        "description": "Mustard Lt",
        "rgbCode": "CCB784"
    },
    {
        "number": "371",
        "description": "Mustard",
        "rgbCode": "BFA671"
    },
    {
        "number": "370",
        "description": "Mustard Medium",
        "rgbCode": "B89D64"
    },
    {
        "number": "834",
        "description": "Golden Olive Vy Lt",
        "rgbCode": "DBBE7F"
    },
    {
        "number": "833",
        "description": "Golden Olive Lt",
        "rgbCode": "C8AB6C"
    },
    {
        "number": "832",
        "description": "Golden Olive",
        "rgbCode": "BD9B51"
    },
    {
        "number": "831",
        "description": "Golden Olive Md",
        "rgbCode": "AA8F56"
    },
    {
        "number": "830",
        "description": "Golden Olive Dk",
        "rgbCode": "8D784B"
    },
    {
        "number": "829",
        "description": "Golden Olive Vy Dk",
        "rgbCode": "7E6B42"
    },
    {
        "number": "613",
        "description": "Drab Brown V Lt",
        "rgbCode": "DCC4AA"
    },
    {
        "number": "612",
        "description": "Drab Brown Lt",
        "rgbCode": "BC9A78"
    },
    {
        "number": "611",
        "description": "Drab Brown",
        "rgbCode": "967656"
    },
    {
        "number": "610",
        "description": "Drab Brown Dk",
        "rgbCode": "796047"
    },
    {
        "number": "3047",
        "description": "Yellow Beige Lt",
        "rgbCode": "E7D6C1"
    },
    {
        "number": "3046",
        "description": "Yellow Beige Md",
        "rgbCode": "D8BC9A"
    },
    {
        "number": "3045",
        "description": "Yellow Beige Dk",
        "rgbCode": "BC966A"
    },
    {
        "number": "167",
        "description": "Yellow Beige V Dk",
        "rgbCode": "A77C49"
    },
    {
        "number": "746",
        "description": "Off White",
        "rgbCode": "FCFCEE"
    },
    {
        "number": "677",
        "description": "Old Gold Vy Lt",
        "rgbCode": "F5ECCB"
    },
    {
        "number": "422",
        "description": "Hazelnut Brown Lt",
        "rgbCode": "C69F7B"
    },
    {
        "number": "3828",
        "description": "Hazelnut Brown",
        "rgbCode": "B78B61"
    },
    {
        "number": "420",
        "description": "Hazelnut Brown Dk",
        "rgbCode": "A07042"
    },
    {
        "number": "869",
        "description": "Hazelnut Brown V Dk",
        "rgbCode": "835E39"
    },
    {
        "number": "728",
        "description": "Topaz",
        "rgbCode": "E4B468"
    },
    {
        "number": "783",
        "description": "Topaz Medium",
        "rgbCode": "CE9124"
    },
    {
        "number": "782",
        "description": "Topaz Dark",
        "rgbCode": "AE7720"
    },
    {
        "number": "781",
        "description": "Topaz Very Dark",
        "rgbCode": "A26D20"
    },
    {
        "number": "780",
        "description": "Topaz Ultra Vy Dk",
        "rgbCode": "94631A"
    },
    {
        "number": "676",
        "description": "Old Gold Lt",
        "rgbCode": "E5CE97"
    },
    {
        "number": "729",
        "description": "Old Gold Medium",
        "rgbCode": "D0A53E"
    },
    {
        "number": "680",
        "description": "Old Gold Dark",
        "rgbCode": "BC8D0E"
    },
    {
        "number": "3829",
        "description": "Old Gold Vy Dark",
        "rgbCode": "A98204"
    },
    {
        "number": "3822",
        "description": "Straw Light",
        "rgbCode": "F6DC98"
    },
    {
        "number": "3821",
        "description": "Straw",
        "rgbCode": "F3CE75"
    },
    {
        "number": "3820",
        "description": "Straw Dark",
        "rgbCode": "DFB65F"
    },
    {
        "number": "3852",
        "description": "Straw Very Dark",
        "rgbCode": "CD9D37"
    },
    {
        "number": "445",
        "description": "Lemon Light",
        "rgbCode": "FFFB8B"
    },
    {
        "number": "307",
        "description": "Lemon",
        "rgbCode": "FDED54"
    },
    {
        "number": "973",
        "description": "Canary Bright",
        "rgbCode": "FFE300"
    },
    {
        "number": "444",
        "description": "Lemon Dark",
        "rgbCode": "FFD600"
    },
    {
        "number": "3078",
        "description": "Golden Yellow Vy Lt",
        "rgbCode": "FDF9CD"
    },
    {
        "number": "727",
        "description": "Topaz Vy Lt",
        "rgbCode": "FFF1AF"
    },
    {
        "number": "726",
        "description": "Topaz Light",
        "rgbCode": "FDD755"
    },
    {
        "number": "725",
        "description": "Topaz Med Lt",
        "rgbCode": "FFC840"
    },
    {
        "number": "972",
        "description": "Canary Deep",
        "rgbCode": "FFB515"
    },
    {
        "number": "745",
        "description": "Yellow Pale Light",
        "rgbCode": "FFE9AD"
    },
    {
        "number": "744",
        "description": "Yellow Pale",
        "rgbCode": "FFE793"
    },
    {
        "number": "743",
        "description": "Yellow Med",
        "rgbCode": "FED376"
    },
    {
        "number": "742",
        "description": "Tangerine Light",
        "rgbCode": "FFBF57"
    },
    {
        "number": "741",
        "description": "Tangerine Med",
        "rgbCode": "FFA32B"
    },
    {
        "number": "740",
        "description": "Tangerine",
        "rgbCode": "FF8B00"
    },
    {
        "number": "970",
        "description": "Pumpkin Light",
        "rgbCode": "F78B13"
    },
    {
        "number": "971",
        "description": "Pumpkin",
        "rgbCode": "F67F00"
    },
    {
        "number": "947",
        "description": "Burnt Orange",
        "rgbCode": "FF7B4D"
    },
    {
        "number": "946",
        "description": "Burnt Orange Med",
        "rgbCode": "EB6307"
    },
    {
        "number": "900",
        "description": "Burnt Orange Dark",
        "rgbCode": "D15807"
    },
    {
        "number": "967",
        "description": "Apricot Very Light",
        "rgbCode": "FFDED5"
    },
    {
        "number": "3824",
        "description": "Apricot Light",
        "rgbCode": "FECDC2"
    },
    {
        "number": "3341",
        "description": "Apricot",
        "rgbCode": "FCAB98"
    },
    {
        "number": "3340",
        "description": "Apricot Med",
        "rgbCode": "FF836F"
    },
    {
        "number": "608",
        "description": "Burnt Orange Bright",
        "rgbCode": "FD5D35"
    },
    {
        "number": "606",
        "description": "Orange?Red Bright",
        "rgbCode": "FA3203"
    },
    {
        "number": "951",
        "description": "Tawny Light",
        "rgbCode": "FFE2CF"
    },
    {
        "number": "3856",
        "description": "Mahogany Ult Vy Lt",
        "rgbCode": "FFD3B5"
    },
    {
        "number": "722",
        "description": "Orange Spice Light",
        "rgbCode": "F7976F"
    },
    {
        "number": "721",
        "description": "Orange Spice Med",
        "rgbCode": "F27842"
    },
    {
        "number": "720",
        "description": "Orange Spice Dark",
        "rgbCode": "E55C1F"
    },
    {
        "number": "3825",
        "description": "Pumpkin Pale",
        "rgbCode": "FDBD96"
    },
    {
        "number": "922",
        "description": "Copper Light",
        "rgbCode": "E27323"
    },
    {
        "number": "921",
        "description": "Copper",
        "rgbCode": "C66218"
    },
    {
        "number": "920",
        "description": "Copper Med",
        "rgbCode": "AC5414"
    },
    {
        "number": "919",
        "description": "Red?Copper",
        "rgbCode": "A64510"
    },
    {
        "number": "918",
        "description": "Red?Copper Dark",
        "rgbCode": "82340A"
    },
    {
        "number": "3770",
        "description": "Tawny Vy Light",
        "rgbCode": "FFEEE3"
    },
    {
        "number": "945",
        "description": "Tawny",
        "rgbCode": "FBD5BB"
    },
    {
        "number": "402",
        "description": "Mahogany Vy Lt",
        "rgbCode": "F7A777"
    },
    {
        "number": "3776",
        "description": "Mahogany Light",
        "rgbCode": "CF7939"
    },
    {
        "number": "301",
        "description": "Mahogany Med",
        "rgbCode": "B35F2B"
    },
    {
        "number": "400",
        "description": "Mahogany Dark",
        "rgbCode": "8F430F"
    },
    {
        "number": "300",
        "description": "Mahogany Vy Dk",
        "rgbCode": "6F2F00"
    },
    {
        "number": "3823",
        "description": "Yellow Ultra Pale",
        "rgbCode": "FFFDE3"
    },
    {
        "number": "3855",
        "description": "Autumn Gold Lt",
        "rgbCode": "FAD396"
    },
    {
        "number": "3854",
        "description": "Autumn Gold Med",
        "rgbCode": "F2AF68"
    },
    {
        "number": "3853",
        "description": "Autumn Gold Dk",
        "rgbCode": "F29746"
    },
    {
        "number": "3827",
        "description": "Golden Brown Pale",
        "rgbCode": "F7BB77"
    },
    {
        "number": "977",
        "description": "Golden Brown Light",
        "rgbCode": "DC9C56"
    },
    {
        "number": "976",
        "description": "Golden Brown Med",
        "rgbCode": "C28142"
    },
    {
        "number": "3826",
        "description": "Golden Brown",
        "rgbCode": "AD7239"
    },
    {
        "number": "975",
        "description": "Golden Brown Dk",
        "rgbCode": "914F12"
    },
    {
        "number": "948",
        "description": "Peach Very Light",
        "rgbCode": "FEE7DA"
    },
    {
        "number": "754",
        "description": "Peach Light",
        "rgbCode": "F7CBBF"
    },
    {
        "number": "3771",
        "description": "Terra Cotta Ult Vy Lt",
        "rgbCode": "F4BBA9"
    },
    {
        "number": "758",
        "description": "Terra Cotta Vy Lt",
        "rgbCode": "EEAA9B"
    },
    {
        "number": "3778",
        "description": "Terra Cotta Light",
        "rgbCode": "D98978"
    },
    {
        "number": "356",
        "description": "Terra Cotta Med",
        "rgbCode": "C56A5B"
    },
    {
        "number": "3830",
        "description": "Terra Cotta",
        "rgbCode": "BC5544"
    },
    {
        "number": "355",
        "description": "Terra Cotta Dark",
        "rgbCode": "984436"
    },
    {
        "number": "3777",
        "description": "Terra Cotta Vy Dk",
        "rgbCode": "863022"
    },
    {
        "number": "3779",
        "description": "Rosewood Ult Vy Lt",
        "rgbCode": "F8CAC8"
    },
    {
        "number": "3859",
        "description": "Rosewood Light",
        "rgbCode": "BA8B7C"
    },
    {
        "number": "3858",
        "description": "Rosewood Med",
        "rgbCode": "964A3F"
    },
    {
        "number": "3857",
        "description": "Rosewood Dark",
        "rgbCode": "68251A"
    },
    {
        "number": "3774",
        "description": "Desert Sand Vy Lt",
        "rgbCode": "F3E1D7"
    },
    {
        "number": "950",
        "description": "Desert Sand Light",
        "rgbCode": "EED3C4"
    },
    {
        "number": "3064",
        "description": "Desert Sand",
        "rgbCode": "C48E70"
    },
    {
        "number": "407",
        "description": "Desert Sand Med",
        "rgbCode": "BB8161"
    },
    {
        "number": "3773",
        "description": "Desert Sand Dark",
        "rgbCode": "B67552"
    },
    {
        "number": "3772",
        "description": "Desert Sand Vy Dk",
        "rgbCode": "A06C50"
    },
    {
        "number": "632",
        "description": "Desert Sand Ult Vy Dk",
        "rgbCode": "875539"
    },
    {
        "number": "453",
        "description": "Shell Gray Light",
        "rgbCode": "D7CECB"
    },
    {
        "number": "452",
        "description": "Shell Gray Med",
        "rgbCode": "C0B3AE"
    },
    {
        "number": "451",
        "description": "Shell Gray Dark",
        "rgbCode": "917B73"
    },
    {
        "number": "3861",
        "description": "Cocoa Light",
        "rgbCode": "A68881"
    },
    {
        "number": "3860",
        "description": "Cocoa",
        "rgbCode": "7D5D57"
    },
    {
        "number": "779",
        "description": "Cocoa Dark",
        "rgbCode": "624B45"
    },
    {
        "number": "712",
        "description": "Cream",
        "rgbCode": "FFFBEF"
    },
    {
        "number": "739",
        "description": "Tan Ult Vy Lt",
        "rgbCode": "F8E4C8"
    },
    {
        "number": "738",
        "description": "Tan Very Light",
        "rgbCode": "ECCC9E"
    },
    {
        "number": "437",
        "description": "Tan Light",
        "rgbCode": "E4BB8E"
    },
    {
        "number": "436",
        "description": "Tan",
        "rgbCode": "CB9051"
    },
    {
        "number": "435",
        "description": "Brown Very Light",
        "rgbCode": "B87748"
    },
    {
        "number": "434",
        "description": "Brown Light",
        "rgbCode": "985E33"
    },
    {
        "number": "433",
        "description": "Brown Med",
        "rgbCode": "7A451F"
    },
    {
        "number": "801",
        "description": "Coffee Brown Dk",
        "rgbCode": "653919"
    },
    {
        "number": "898",
        "description": "Coffee Brown Vy Dk",
        "rgbCode": "492A13"
    },
    {
        "number": "938",
        "description": "Coffee Brown Ult Dk",
        "rgbCode": "361F0E"
    },
    {
        "number": "3371",
        "description": "Black Brown",
        "rgbCode": "1E1108"
    },
    {
        "number": "543",
        "description": "Beige Brown Ult Vy Lt",
        "rgbCode": "F2E3CE"
    },
    {
        "number": "3864",
        "description": "Mocha Beige Light",
        "rgbCode": "CBB69C"
    },
    {
        "number": "3863",
        "description": "Mocha Beige Med",
        "rgbCode": "A4835C"
    },
    {
        "number": "3862",
        "description": "Mocha Beige Dark",
        "rgbCode": "8A6E4E"
    },
    {
        "number": "3031",
        "description": "Mocha Brown Vy Dk",
        "rgbCode": "4B3C2A"
    },
    {
        "number": "B5200",
        "description": "Snow White",
        "rgbCode": "FFFFFF"
    },
    {
        "number": "White",
        "description": "White",
        "rgbCode": "FCFBF8"
    },
    {
        "number": "3865",
        "description": "Winter White",
        "rgbCode": "F9F7F1"
    },
    {
        "number": "Ecru",
        "description": "Ecru",
        "rgbCode": "F0EADA"
    },
    {
        "number": "822",
        "description": "Beige Gray Light",
        "rgbCode": "E7E2D3"
    },
    {
        "number": "644",
        "description": "Beige Gray Med",
        "rgbCode": "DDD8CB"
    },
    {
        "number": "642",
        "description": "Beige Gray Dark",
        "rgbCode": "A49878"
    },
    {
        "number": "640",
        "description": "Beige Gray Vy Dk",
        "rgbCode": "857B61"
    },
    {
        "number": "3787",
        "description": "Brown Gray Dark",
        "rgbCode": "625D50"
    },
    {
        "number": "3021",
        "description": "Brown Gray Vy Dk",
        "rgbCode": "4F4B41"
    },
    {
        "number": "3024",
        "description": "Brown Gray Vy Lt",
        "rgbCode": "EBEAE7"
    },
    {
        "number": "3023",
        "description": "Brown Gray Light",
        "rgbCode": "B1AA97"
    },
    {
        "number": "3022",
        "description": "Brown Gray Med",
        "rgbCode": "8E9078"
    },
    {
        "number": "535",
        "description": "Ash Gray Vy Lt",
        "rgbCode": "636458"
    },
    {
        "number": "3033",
        "description": "Mocha Brown Vy Lt",
        "rgbCode": "E3D8CC"
    },
    {
        "number": "3782",
        "description": "Mocha Brown Lt",
        "rgbCode": "D2BCA6"
    },
    {
        "number": "3032",
        "description": "Mocha Brown Med",
        "rgbCode": "B39F8B"
    },
    {
        "number": "3790",
        "description": "Beige Gray Ult Dk",
        "rgbCode": "7F6A55"
    },
    {
        "number": "3781",
        "description": "Mocha Brown Dk",
        "rgbCode": "6B5743"
    },
    {
        "number": "3866",
        "description": "Mocha Brn Ult Vy Lt",
        "rgbCode": "FAF6F0"
    },
    {
        "number": "842",
        "description": "Beige Brown Vy Lt",
        "rgbCode": "D1BAA1"
    },
    {
        "number": "841",
        "description": "Beige Brown Lt",
        "rgbCode": "B69B7E"
    },
    {
        "number": "840",
        "description": "Beige Brown Med",
        "rgbCode": "9A7C5C"
    },
    {
        "number": "839",
        "description": "Beige Brown Dk",
        "rgbCode": "675541"
    },
    {
        "number": "838",
        "description": "Beige Brown Vy Dk",
        "rgbCode": "594937"
    },
    {
        "number": "3072",
        "description": "Beaver Gray Vy Lt",
        "rgbCode": "E6E8E8"
    },
    {
        "number": "648",
        "description": "Beaver Gray Lt",
        "rgbCode": "BCB4AC"
    },
    {
        "number": "647",
        "description": "Beaver Gray Med",
        "rgbCode": "B0A69C"
    },
    {
        "number": "646",
        "description": "Beaver Gray Dk",
        "rgbCode": "877D73"
    },
    {
        "number": "645",
        "description": "Beaver Gray Vy Dk",
        "rgbCode": "6E655C"
    },
    {
        "number": "844",
        "description": "Beaver Gray Ult Dk",
        "rgbCode": "484848"
    },
    {
        "number": "762",
        "description": "Pearl Gray Vy Lt",
        "rgbCode": "ECECEC"
    },
    {
        "number": "415",
        "description": "Pearl Gray",
        "rgbCode": "D3D3D6"
    },
    {
        "number": "318",
        "description": "Steel Gray Lt",
        "rgbCode": "ABABAB"
    },
    {
        "number": "414",
        "description": "Steel Gray Dk",
        "rgbCode": "8C8C8C"
    },
    {
        "number": "168",
        "description": "Pewter Very Light",
        "rgbCode": "D1D1D1"
    },
    {
        "number": "169",
        "description": "Pewter Light",
        "rgbCode": "848484"
    },
    {
        "number": "317",
        "description": "Pewter Gray",
        "rgbCode": "6C6C6C"
    },
    {
        "number": "413",
        "description": "Pewter Gray Dark",
        "rgbCode": "565656"
    },
    {
        "number": "3799",
        "description": "Pewter Gray Vy Dk",
        "rgbCode": "424242"
    },
    {
        "number": "310",
        "description": "Black",
        "rgbCode": "000000"
    }
]